{
  "id": "240560d7398eb5f1",
  "title": "城北的花 (Live)",
  "artists": [
    "王源",
    "王宇宙Leto"
  ],
  "album": "天赐的声音第六季 第4期",
  "albums": [
    "天赐的声音第六季 第4期",
    "天赐的声音第六季 第4期 (Live)"
  ],
  "language": "zh-Hans",
  "hasTranslation": false,
  "hasTransliteration": false,
  "aliases": [],
  "sourceIds": {
    "qqMusicId": "004KdciZ1NKT2c",
    "ncmMusicId": "2702711900",
    "appleMusicId": "1813692079"
  },
  "author": {
    "githubId": "76586484",
    "githubLogin": "2755337087"
  },
  "license": "",
  "sourceUrl": ""
}
